macro_gen/__init__.py
macro_gen/actiongenerator.py
macro_gen/executioncontroller.py
macro_gen/inputrecorder.py
macro_gen/main.py
macro_gen/templates.py
macro_gen/utils.py
macro_gen-0.1.0.data/data/share/man/man8/macro-gen.8
macro_gen-0.1.0.dist-info/METADATA
macro_gen-0.1.0.dist-info/WHEEL
macro_gen-0.1.0.dist-info/entry_points.txt
macro_gen-0.1.0.dist-info/top_level.txt
macro_gen-0.1.0.dist-info/RECORD
