Metadata-Version: 2.4
Name: macro-gen
Version: 0.1.0
Summary: A tool to record and replay mouse and keyboard actions
Home-page: https://github.com/0xTristo/macro-gen
Author: Ali Terro
Author-email: aliterr588@gmail.com
Classifier: Programming Language :: Python :: 3
Classifier: License :: OSI Approved :: MIT License
Classifier: Operating System :: OS Independent
Requires-Python: >=3.6
Requires-Dist: pynput>=1.7.0
Requires-Dist: configparser>=5.0.0
Dynamic: author
Dynamic: author-email
Dynamic: classifier
Dynamic: description
Dynamic: description-content-type
Dynamic: home-page
Dynamic: requires-dist
Dynamic: requires-python
Dynamic: summary
